LinkedList/CircularLinkedList.py
LinkedList/DoubleCircularLinkedList.py
LinkedList/DoubleLinkedList.py
LinkedList/SinglyLinkedList.py
LinkedList/__init__.py
Queue/CircularQueue.py
Queue/Huffman.py
Queue/MaxHeap.py
Queue/QueueArray.py
Queue/QueueLL.py
Queue/__init__.py
Sorting/MergeSort.py
Sorting/__init__.py
Stack/InfixtoPostfix.py
Stack/InfixtoPrefix.py
Stack/LinearStack.py
Stack/LinkedStack.py
Stack/__init__.py
HtnayajDSAlgoPy-0.1.0.dist-info/METADATA
HtnayajDSAlgoPy-0.1.0.dist-info/WHEEL
HtnayajDSAlgoPy-0.1.0.dist-info/top_level.txt
HtnayajDSAlgoPy-0.1.0.dist-info/RECORD
